{"admin\/css\/style.css":{"path":"static\/@dev__2229048__style.css","cache":"ifq569U5YI"},"admin\/js\/data-siswa.js":{"path":"static\/@dev__3225725__data_siswa.js","cache":"B2Q5TQMet0"},"admin\/js\/functions.js":{"path":"static\/@dev__7989588__functions.js","cache":"LBFfzsvBZx"},"admin\/js\/main.js":{"path":"static\/@dev__0762468__main.js","cache":"8nOMaTxURD"},"css\/font.css":{"path":"static\/@dev__5117022__font.css","cache":"CwUBQB3Bdy"},"css\/guest_responsive.css":{"path":"static\/@dev__9684275__guest_responsive.css","cache":"7qNLMZpcyr"},"css\/guest_style.css":{"path":"static\/@dev__6716527__guest_style.css","cache":"i5zJ61xZww"},"img\/2.jpg":{"path":"static\/@dev__2005463__2.jpg","cache":"zcBElHAYIz"},"img\/3.jpg":{"path":"static\/@dev__2197703__3.jpg","cache":"lZcHE4K4NW"},"img\/4.jpg":{"path":"static\/@dev__2688412__4.jpg","cache":"mEQvnVi0eT"},"img\/5.jpg":{"path":"static\/@dev__1112156__5.jpg","cache":"v5R8MZKr0z"},"img\/6.jpg":{"path":"static\/@dev__4778259__6.jpg","cache":"iWgwR6dtfM"},"img\/logo.png":{"path":"static\/@dev__2993544__logo.png","cache":"aCsHAUP7Wc"},"img\/no-file-found.jpg":{"path":"static\/@dev__9617014__no_file_found.jpg","cache":"i6rgBWBeK8"},"img\/no-image.jpg":{"path":"static\/@dev__4940850__no_image.jpg","cache":"eJFw3ANnkP"},"img\/no-profile.jpg":{"path":"static\/@dev__0899792__no_profile.jpg","cache":"vBDPOkES2r"},"js\/guest_script.js":{"path":"static\/@dev__2118836__guest_script.js","cache":"rBaWeDLSJz"},"null-name-itu":{"path":"static\/@dev__6769714__null_name_itu","cache":"lEkTV9Nj8W"},"siswa\/css\/responsive.css":{"path":"static\/@dev__5823395__responsive.css","cache":"ep0AsMlpVo"},"siswa\/css\/style.css":{"path":"static\/@dev__3500002__style.css","cache":"S6duBu2J9B"},"siswa\/js\/functions.js":{"path":"static\/@dev__9164990__functions.js","cache":"gwCzGBDNnT"},"siswa\/js\/script.js":{"path":"static\/@dev__6287023__script.js","cache":"X8ZoqZACAi"}}